S3/ACL.py
S3/AccessLog.py
S3/BaseUtils.py
S3/BidirMap.py
S3/CloudFront.py
S3/Config.py
S3/ConnMan.py
S3/Crypto.py
S3/Custom_httplib27.py
S3/Custom_httplib3x.py
S3/Exceptions.py
S3/ExitCodes.py
S3/FileDict.py
S3/FileLists.py
S3/HashCache.py
S3/MultiPart.py
S3/PkgInfo.py
S3/Progress.py
S3/S3.py
S3/S3Uri.py
S3/SortedDict.py
S3/Utils.py
S3/__init__.py
s3cmd-2.4.0.data/data/share/doc/packages/s3cmd/INSTALL.md
s3cmd-2.4.0.data/data/share/doc/packages/s3cmd/LICENSE
s3cmd-2.4.0.data/data/share/doc/packages/s3cmd/NEWS
s3cmd-2.4.0.data/data/share/doc/packages/s3cmd/README.md
s3cmd-2.4.0.data/data/share/man/man1/s3cmd.1
s3cmd-2.4.0.data/scripts/s3cmd
s3cmd-2.4.0.dist-info/LICENSE
s3cmd-2.4.0.dist-info/METADATA
s3cmd-2.4.0.dist-info/WHEEL
s3cmd-2.4.0.dist-info/top_level.txt
s3cmd-2.4.0.dist-info/RECORD
